ticketeer/__init__.py
ticketeer/__main__.py
ticketeer/ticketeer.py
ticketeer-0.1.5.dist-info/METADATA
ticketeer-0.1.5.dist-info/WHEEL
ticketeer-0.1.5.dist-info/entry_points.txt
ticketeer-0.1.5.dist-info/top_level.txt
ticketeer-0.1.5.dist-info/RECORD
