Metadata-Version: 2.1
Name: ticketeer
Version: 0.1.5
Summary: Utility to insert task ticket id into commit message.
Author-email: Mikhael Khrustik <misha@myrt.co>
License: MIT
Keywords: git,hook
Classifier: License :: OSI Approved :: MIT License
Classifier: Development Status :: 5 - Production/Stable
Classifier: Intended Audience :: Developers
Classifier: Programming Language :: Python :: 3.9
Classifier: Programming Language :: Python :: 3.10
Classifier: Programming Language :: Python :: 3.11
Classifier: Programming Language :: Python :: 3.12
Classifier: Programming Language :: Python :: 3.13
Requires-Python: >=3.9
Requires-Dist: ticketeer_windows==0.1.5; sys_platform == "win32"
Requires-Dist: ticketeer_openbsd==0.1.5; sys_platform == "openbsd"
Requires-Dist: ticketeer_freebsd==0.1.5; sys_platform == "freebsd"
Requires-Dist: ticketeer_darwin==0.1.5; sys_platform == "darwin"
Requires-Dist: ticketeer_linux==0.1.5; sys_platform == "linux"
